secbench_ext_processing-0.2.4.dist-info/METADATA
secbench_ext_processing-0.2.4.dist-info/WHEEL
secbench_ext_processing-0.2.4.dist-info/licenses/LICENSE
secbench_ext_processing/__init__.py
secbench_ext_processing/secbench_ext_processing.abi3.so
secbench_ext_processing-0.2.4.dist-info/RECORD
