Metadata-Version: 2.4
Name: secbench_ext_processing
Version: 0.2.4
Classifier: Programming Language :: Python :: 3
Classifier: Programming Language :: Python :: 3 :: Only
Classifier: Programming Language :: Python :: 3.10
Classifier: Programming Language :: Python :: 3.11
Classifier: Programming Language :: Python :: 3.12
Classifier: Programming Language :: Python :: 3.13
Classifier: Topic :: Security
Classifier: Topic :: Scientific/Engineering
Classifier: Intended Audience :: Developers
Classifier: Intended Audience :: Science/Research
Classifier: License :: OSI Approved :: CEA CNRS Inria Logiciel Libre License, version 2.1 (CeCILL-2.1)
License-File: LICENSE
Summary: Extension module containing Rust-accelerated side-channel processing tools
Author-email: Secbench team <support@secbench.fr>
Requires-Python: >=3.10
Project-URL: Homepage, https://doc.secbench.fr
Project-URL: Bug Reports, https://github.com/CEA-Leti/secbench/issues
Project-URL: Source, https://github.com/CEA-Leti/secbench
